{"cameraMode":{"drawMode":0,"name":"Shaded","section":"Shading Mode"},"sceneLighting":false,"audioPlay":false,"sceneViewState":{"showFog":true,"showMaterialUpdate":false,"showSkybox":false,"showFlares":true,"showImageEffects":true,"showParticleSystems":true},"in2DMode":false,"pivot":{"x":16.32196807861328,"y":-2.4462075233459474,"z":1.1690845489501954},"rotation":{"x":0.21527284383773805,"y":0.772956371307373,"z":-0.33853679895401,"w":0.49151700735092165},"size":6.492786407470703,"orthographic":false}